bayesian_torch/__init__.py
bayesian_torch/ao/__init__.py
bayesian_torch/ao/nn/__init__.py
bayesian_torch/ao/nn/quantized/__init__.py
bayesian_torch/ao/quantization/__init__.py
bayesian_torch/ao/quantization/quantize.py
bayesian_torch/layers/__init__.py
bayesian_torch/layers/base_variational_layer.py
bayesian_torch/layers/batchnorm.py
bayesian_torch/layers/dropout.py
bayesian_torch/layers/relu.py
bayesian_torch/layers/flipout_layers/__init__.py
bayesian_torch/layers/flipout_layers/conv_flipout.py
bayesian_torch/layers/flipout_layers/linear_flipout.py
bayesian_torch/layers/flipout_layers/quantized_conv_flipout.py
bayesian_torch/layers/flipout_layers/quantized_linear_flipout.py
bayesian_torch/layers/flipout_layers/rnn_flipout.py
bayesian_torch/layers/variational_layers/__init__.py
bayesian_torch/layers/variational_layers/conv_variational.py
bayesian_torch/layers/variational_layers/linear_variational.py
bayesian_torch/layers/variational_layers/quantize_conv_variational.py
bayesian_torch/layers/variational_layers/quantize_linear_variational.py
bayesian_torch/layers/variational_layers/rnn_variational.py
bayesian_torch/models/__init__.py
bayesian_torch/models/bnn_to_qbnn.py
bayesian_torch/models/dnn_to_bnn.py
bayesian_torch/models/bayesian/__init__.py
bayesian_torch/models/bayesian/quantized_resnet_flipout_large.py
bayesian_torch/models/bayesian/quantized_resnet_variational_large.py
bayesian_torch/models/bayesian/resnet_flipout.py
bayesian_torch/models/bayesian/resnet_flipout_large.py
bayesian_torch/models/bayesian/resnet_variational.py
bayesian_torch/models/bayesian/resnet_variational_large.py
bayesian_torch/models/bayesian/simple_cnn_variational.py
bayesian_torch/models/deterministic/__init__.py
bayesian_torch/models/deterministic/resnet.py
bayesian_torch/models/deterministic/resnet_large.py
bayesian_torch/models/deterministic/simple_cnn.py
bayesian_torch/models/flipout/__init__.py
bayesian_torch/models/flipout/resnet.py
bayesian_torch/models/flipout/simple_cnn.py
bayesian_torch-0.5.0.dist-info/LICENSE
bayesian_torch-0.5.0.dist-info/METADATA
bayesian_torch-0.5.0.dist-info/WHEEL
bayesian_torch-0.5.0.dist-info/top_level.txt
bayesian_torch-0.5.0.dist-info/RECORD
