Metadata-Version: 2.1
Name: bayesian-torch
Version: 0.5.0
Summary: A library for Bayesian neural network layers and uncertainty estimation in Deep Learning
Home-page: https://github.com/IntelLabs/bayesian-torch
Author: Intel Labs
Author-email: ranganath.krishnan@intel.com
Classifier: Development Status :: 3 - Alpha
Classifier: Intended Audience :: Developers
Classifier: Intended Audience :: Science/Research
Classifier: Programming Language :: Python :: 3
Classifier: Programming Language :: Python :: 3.7
Classifier: Topic :: Scientific/Engineering
Classifier: Topic :: Scientific/Engineering :: Artificial Intelligence
Classifier: Topic :: Software Development :: Libraries
Classifier: Topic :: Software Development :: Libraries :: Python Modules
License-File: LICENSE
